GPUQuantile/__init__.py
GPUQuantile/ddsketch/__init__.py
GPUQuantile/ddsketch/core.py
GPUQuantile/ddsketch/mapping/__init__.py
GPUQuantile/ddsketch/mapping/base.py
GPUQuantile/ddsketch/mapping/cubic_interpolation.py
GPUQuantile/ddsketch/mapping/linear_interpolation.py
GPUQuantile/ddsketch/mapping/logarithmic.py
GPUQuantile/ddsketch/storage/__init__.py
GPUQuantile/ddsketch/storage/base.py
GPUQuantile/ddsketch/storage/contiguous.py
GPUQuantile/ddsketch/storage/sparse.py
GPUQuantile/hdrhistogram/__init__.py
GPUQuantile/hdrhistogram/core.py
GPUQuantile/momentsketch/__init__.py
GPUQuantile/momentsketch/core.py
GPUQuantile/momentsketch/example.py
GPUQuantile/momentsketch/optimizer.py
GPUQuantile/momentsketch/simple_moment_sketch.py
GPUQuantile/momentsketch/utils.py
docs/__init__.py
docs/conf.py
gpuquantile-0.0.4.dist-info/licenses/LICENSE
tests/__init__.py
tests/hdrhistogram/__init__.py
tests/hdrhistogram/test_hdr.py
tests/momentsketch/__init__.py
tests/momentsketch/core_test.py
tests/momentsketch/integration_test.py
tests/momentsketch/optimizer_test.py
tests/momentsketch/simple_ms_test.py
tests/momentsketch/utils_test.py
gpuquantile-0.0.4.dist-info/METADATA
gpuquantile-0.0.4.dist-info/WHEEL
gpuquantile-0.0.4.dist-info/top_level.txt
gpuquantile-0.0.4.dist-info/RECORD
